[
  {
    "outputFileName": "Content/layout.bundle.css",
    "inputFiles": [
      "Content/bootstrap/bootstrap.css",
      "Content/layout.css"
    ],
    "minify": {
      "enabled": true,
      "commentMode": "none"
    }
  },
  {
    "outputFileName": "Scripts/layout.bundle.js",
    "inputFiles": [
      "Scripts/modernizr-2.8.3.js",
      "Scripts/respond.js",
      "Scripts/jquery-1.12.4.js",
      "Scripts/bootstrap.js"
    ],
    "minify": {
      "enabled": true,
      "preserveImportantComments": false
    }
  },
  {
    "outputFileName": "Scripts/form.bundle.js",
    "inputFiles": [
      "Scripts/jquery.validate.js",
      "Scripts/jquery.validate.unobtrusive.js",
      "Scripts/jquery.validate.extensions.js",
      "Scripts/jquery.preview.unobtrusive.js",
      "Scripts/jquery.autosize.unobtrusive.js"
    ],
    "minify": {
      "enabled": true,
      "preserveImportantComments": false
    }
  },
  {
    "outputFileName": "Scripts/autocomplete.bundle.js",
    "inputFiles": [
      "Scripts/jquery-ui.js",
      "Scripts/jquery.autocomplete.unobtrusive.js"
    ],
    "minify": {
      "enabled": true,
      "preserveImportantComments": false
    }
  },
  {
    "outputFileName": "Content/jquery-ui.min.css",
    "inputFiles": [
      "Content/jquery-ui.css"
    ]
  },
  {
    "outputFileName": "Content/datatables.min.css",
    "inputFiles": [
      "Content/datatables.css"
    ]
  },
  {
    "outputFileName": "Scripts/datatables.bundle.js",
    "inputFiles": [
      "Scripts/datatables.js",
      "Scripts/datatables.unobtursive.js"
    ]
  }
]
